{
  "identifier": "",
  "motion_text": "Reported favorably out of committee",
  "motion_classification": [
    "passage"
  ],
  "start_date": "2026-06-15T04:00:00+00:00",
  "result": "pass",
  "organization": "~{\"classification\": \"lower\"}",
  "legislative_session": "222",
  "bill": "58481502-7dc8-11f1-892c-d667d338ec28",
  "bill_action": null,
  "bill_identifier": "A3094",
  "votes": [
    {
      "option": "yes",
      "voter_name": "Kennedy, James J.",
      "voter_id": "~{\"name\": \"Kennedy, James J.\"}",
      "note": ""
    },
    {
      "option": "yes",
      "voter_name": "Sauickie, Alex",
      "voter_id": "~{\"name\": \"Sauickie, Alex\"}",
      "note": ""
    },
    {
      "option": "yes",
      "voter_name": "Simmons, Heather",
      "voter_id": "~{\"name\": \"Simmons, Heather\"}",
      "note": ""
    },
    {
      "option": "yes",
      "voter_name": "Fantasia, Dawn",
      "voter_id": "~{\"name\": \"Fantasia, Dawn\"}",
      "note": ""
    },
    {
      "option": "yes",
      "voter_name": "Katz, Andrea",
      "voter_id": "~{\"name\": \"Katz, Andrea\"}",
      "note": ""
    },
    {
      "option": "yes",
      "voter_name": "Sweeney, Marisa",
      "voter_id": "~{\"name\": \"Sweeney, Marisa\"}",
      "note": ""
    }
  ],
  "counts": [
    {
      "option": "yes",
      "value": 6
    },
    {
      "option": "no",
      "value": 0
    },
    {
      "option": "other",
      "value": 0
    }
  ],
  "sources": [
    {
      "url": "https://www.njleg.state.nj.us/downloads.asp",
      "note": ""
    },
    {
      "url": "https://www.njleg.state.nj.us/downloads.asp",
      "note": ""
    }
  ],
  "extras": {},
  "dedupe_key": "A3094_lower_Reported_favorably_out_of_committee_AAN"
}